osgiservicebridge/__init__.py
osgiservicebridge/bridge.py
osgiservicebridge/exporter_pb2.py
osgiservicebridge/flatbuf.py
osgiservicebridge/protobuf.py
osgiservicebridge/version.py
osgiservicebridge-1.5.9.dist-info/licenses/LICENSE
osgiservicebridge-1.5.9.dist-info/METADATA
osgiservicebridge-1.5.9.dist-info/WHEEL
osgiservicebridge-1.5.9.dist-info/top_level.txt
osgiservicebridge-1.5.9.dist-info/RECORD
